{
  "schema_version": "jobsight.description.v1",
  "hash": "cc361aa3ef339ae25d03ec36c902989b",
  "source_url": "https://eastgippsland.pulsesoftware.com/Pulse/job/muszh3/Governance-Officer?source=public",
  "source_id": "east-gippsland-pulse",
  "text": "We are East Gippsland Shire East Gippsland is a natural playground with over 21,000 square km of land including ski fields, high country, nine national parks, two significant marine parks, Australia’s largest navigable inland lake system and stunning coastlines included! Business Unit The...",
  "html": null,
  "sections": [],
  "extracted_at": "2026-05-29T04:51:29Z"
}
