{
  "schema_version": "jobsight.description.v1",
  "hash": "0f1048ce7b1baf636087119596af0132",
  "source_url": "https://maribyrnong.recruitmenthub.com.au/Vacancies/",
  "source_id": "maribyrnong-recruitmenthub",
  "text": "Permanent Full-Time Band 7 ($111,073 - $123,429) + 12% super + monthly ADO Maribyrnong Aquatic Centre (MAC). Manage all aspects of the service delivery for aquatic programs, events, supervision, childcare and swimming and water safety education at MAC. (Read more)",
  "html": null,
  "sections": [],
  "extracted_at": "2026-05-28T07:07:46Z"
}
