{
  "schema_version": "jobsight.description.v1",
  "hash": "37385c06ec929e68d4980b92f2ac4c7b",
  "source_url": "https://banyule.pulsesoftware.com/Pulse/job/oPQumY/Early-Childhood-Educator-Cert-III-Inclusion-Support-9860722?source=public",
  "source_id": "banyule-pulse",
  "text": "Shape the future of Banyule’s youngest community members through quality early childhood education. Make a meaningful difference in children’s early years by joining a supportive and passionate team. In this role, you’ll deliver a high-quality education and care program for children from birth to...",
  "html": null,
  "sections": [],
  "extracted_at": "2026-07-02T19:39:31Z"
}
