{
  "schema_version": "jobsight.description.v1",
  "hash": "493a7904529f049f5b704d8407758b88",
  "source_url": "https://employmenthero.com/jobs/position/towong-shire-council-customer-service-officer-yrm5g/",
  "source_id": "towong-employmenthero",
  "text": "Customer Service Officer Permanent part-time role, 32 hours, four days per week. Join a small team in a relaxing environment based in Tallangatta. Study Leave provisions, and secondment and career growth opportunities. In this role, you will Provide accurate and timely information to the community...",
  "html": null,
  "sections": [],
  "extracted_at": "2026-06-19T06:20:30Z"
}
